[[null,1,1486438967,1486438967,"20170206","{\"visits\":1,\"hits\":1,\"pageviews\":1,\"timeOnSite\":null,\"bounces\":1,\"transactions\":null,\"transactionRevenue\":null,\"newVisits\":1,\"screenviews\":null,\"uniqueScreenviews\":null,\"timeOnScreen\":null,\"totalTransactionRevenue\":null,\"sessionQualityDim\":null}","{\"referralPath\":null,\"campaign\":\"(not set)\",\"source\":\"(direct)\",\"medium\":\"(none)\",\"keyword\":null,\"adContent\":null,\"adwordsClickInfo\":{\"campaignId\":null,\"adGroupId\":null,\"creativeId\":null,\"criteriaId\":null,\"page\":null,\"slot\":null,\"criteriaParameters\":\"not available in demo dataset\",\"gclId\":null,\"customerId\":null,\"adNetworkType\":null,\"targetingCriteria\":null,\"isVideoAd\":null},\"isTrueDirect\":null,\"campaignCode\":null}","{\"browser\":\"Chrome\",\"browserVersion\":\"not available in demo dataset\",\"browserSize\":\"not available in demo dataset\",\"operatingSystem\":\"Windows\",\"operatingSystemVersion\":\"not available in demo dataset\",\"isMobile\":false,\"mobileDeviceBranding\":\"not available in demo dataset\",\"mobileDeviceModel\":\"not available in demo dataset\",\"mobileInputSelector\":\"not available in demo dataset\",\"mobileDeviceInfo\":\"not available in demo dataset\",\"mobileDeviceMarketingName\":\"not available in demo dataset\",\"flashVersion\":\"not available in demo dataset\",\"javaEnabled\":null,\"language\":\"not available in demo dataset\",\"screenColors\":\"not available in demo dataset\",\"screenResolution\":\"not available in demo dataset\",\"deviceCategory\":\"desktop\"}","{\"continent\":\"Asia\",\"subContinent\":\"Eastern Asia\",\"country\":\"Hong Kong\",\"region\":\"(not set)\",\"metro\":\"(not set)\",\"city\":\"Hong Kong\",\"cityId\":\"not available in demo dataset\",\"networkDomain\":\"hkserverdomain.com\",\"latitude\":\"not available in demo dataset\",\"longitude\":\"not available in demo dataset\",\"networkLocation\":\"not available in demo dataset\"}","[]","[{'hitNumber': 1, 'time': 0, 'hour': 19, 'minute': 42, 'isSecure': None, 'isInteraction': True, 'isEntrance': True, 'isExit': True, 'referer': 'https://www.google.com.hk/', 'page': {'pagePath': '/google+redesign/electronics/accessories/google+electronics+accessory+pouch.axd', 'hostname': 'shop.googlemerchandisestore.com', 'pageTitle': 'Google Electronics Accessory Pouch', 'searchKeyword': None, 'searchCategory': None, 'pagePathLevel1': '/google+redesign/', 'pagePathLevel2': '/electronics/', 'pagePathLevel3': '/accessories/', 'pagePathLevel4': '/google+electronics+accessory+pouch.axd'}, 'transaction': {'transactionId': None, 'transactionRevenue': None, 'transactionTax': None, 'transactionShipping': None, 'affiliation': None, 'currencyCode': 'USD', 'localTransactionRevenue': None, 'localTransactionTax': None, 'localTransactionShipping': None, 'transactionCoupon': None}, 'item': {'transactionId': None, 'productName': None, 'productCategory': None, 'productSku': None, 'itemQuantity': None, 'itemRevenue': None, 'currencyCode': 'USD', 'localItemRevenue': None}, 'contentInfo': None, 'appInfo': {'name': None, 'version': None, 'id': None, 'installerId': None, 'appInstallerId': None, 'appName': None, 'appVersion': None, 'appId': None, 'screenName': 'shop.googlemerchandisestore.com/google+redesign/electronics/accessories/google+electronics+accessory+pouch.axd', 'landingScreenName': 'shop.googlemerchandisestore.com/google+redesign/electronics/accessories/google+electronics+accessory+pouch.axd', 'exitScreenName': 'shop.googlemerchandisestore.com/google+redesign/electronics/accessories/google+electronics+accessory+pouch.axd', 'screenDepth': '0'}, 'exceptionInfo': {'description': None, 'isFatal': True, 'exceptions': None, 'fatalExceptions': None}, 'eventInfo': None, 'product': array([{'productSKU': '9182714', 'v2ProductName': \"Google Men's Long Sleeve Raglan Ocean Blue\", 'v2ProductCategory': '(not set)', 'productVariant': '(not set)', 'productBrand': '(not set)', 'productRevenue': None, 'localProductRevenue': None, 'productPrice': 0, 'localProductPrice': 0, 'productQuantity': None, 'productRefundAmount': None, 'localProductRefundAmount': None, 'isImpression': True, 'isClick': None, 'customDimensions': array([], dtype=object), 'customMetrics': array([], dtype=object), 'productListName': 'Related Products', 'productListPosition': 1},\n        {'productSKU': '9182502', 'v2ProductName': \"Google Women's Yoga Jacket Black\", 'v2ProductCategory': '(not set)', 'productVariant': '(not set)', 'productBrand': '(not set)', 'productRevenue': None, 'localProductRevenue': None, 'productPrice': 0, 'localProductPrice': 0, 'productQuantity': None, 'productRefundAmount': None, 'localProductRefundAmount': None, 'isImpression': True, 'isClick': None, 'customDimensions': array([], dtype=object), 'customMetrics': array([], dtype=object), 'productListName': 'Related Products', 'productListPosition': 2}],\n       dtype=object), 'promotion': array([], dtype=object), 'promotionActionInfo': None, 'refund': None, 'eCommerceAction': {'action_type': '0', 'step': 1, 'option': None}, 'experiment': array([], dtype=object), 'publisher': None, 'customVariables': array([], dtype=object), 'customDimensions': array([], dtype=object), 'customMetrics': array([], dtype=object), 'type': 'PAGE', 'social': {'socialInteractionNetwork': None, 'socialInteractionAction': None, 'socialInteractions': None, 'socialInteractionTarget': None, 'socialNetwork': '(not set)', 'uniqueSocialInteractions': None, 'hasSocialSourceReferral': 'No', 'socialInteractionNetworkAction': ' : '}, 'latencyTracking': None, 'sourcePropertyInfo': None, 'contentGroup': {'contentGroup1': '(not set)', 'contentGroup2': 'Electronics', 'contentGroup3': '(not set)', 'contentGroup4': '(not set)', 'contentGroup5': '(not set)', 'previousContentGroup1': '(entrance)', 'previousContentGroup2': '(entrance)', 'previousContentGroup3': '(entrance)', 'previousContentGroup4': '(entrance)', 'previousContentGroup5': '(entrance)', 'contentGroupUniqueViews1': None, 'contentGroupUniqueViews2': 1, 'contentGroupUniqueViews3': None, 'contentGroupUniqueViews4': None, 'contentGroupUniqueViews5': None}, 'dataSource': None, 'publisher_infos': array([], dtype=object)}                                                                                                                                                                                                                                                                                                                                                                                                                                                                                                                                                                                                                                                                                                                                                                                                                                                                                                                                                                                                                                                                                              ]","7091819408040344553",null,"Organic Search","Not Socially Engaged"],[null,1,1486427307,1486427307,"20170206","{\"visits\":1,\"hits\":1,\"pageviews\":1,\"timeOnSite\":null,\"bounces\":1,\"transactions\":null,\"transactionRevenue\":null,\"newVisits\":1,\"screenviews\":null,\"uniqueScreenviews\":null,\"timeOnScreen\":null,\"totalTransactionRevenue\":null,\"sessionQualityDim\":null}","{\"referralPath\":null,\"campaign\":\"(not set)\",\"source\":\"(direct)\",\"medium\":\"(none)\",\"keyword\":null,\"adContent\":null,\"adwordsClickInfo\":{\"campaignId\":null,\"adGroupId\":null,\"creativeId\":null,\"criteriaId\":null,\"page\":null,\"slot\":null,\"criteriaParameters\":\"not available in demo dataset\",\"gclId\":null,\"customerId\":null,\"adNetworkType\":null,\"targetingCriteria\":null,\"isVideoAd\":null},\"isTrueDirect\":null,\"campaignCode\":null}","{\"browser\":\"Chrome\",\"browserVersion\":\"not available in demo dataset\",\"browserSize\":\"not available in demo dataset\",\"operatingSystem\":\"Windows\",\"operatingSystemVersion\":\"not available in demo dataset\",\"isMobile\":false,\"mobileDeviceBranding\":\"not available in demo dataset\",\"mobileDeviceModel\":\"not available in demo dataset\",\"mobileInputSelector\":\"not available in demo dataset\",\"mobileDeviceInfo\":\"not available in demo dataset\",\"mobileDeviceMarketingName\":\"not available in demo dataset\",\"flashVersion\":\"not available in demo dataset\",\"javaEnabled\":null,\"language\":\"not available in demo dataset\",\"screenColors\":\"not available in demo dataset\",\"screenResolution\":\"not available in demo dataset\",\"deviceCategory\":\"desktop\"}","{\"continent\":\"Americas\",\"subContinent\":\"South America\",\"country\":\"Venezuela\",\"region\":\"not available in demo dataset\",\"metro\":\"not available in demo dataset\",\"city\":\"not available in demo dataset\",\"cityId\":\"not available in demo dataset\",\"networkDomain\":\"cantv.net\",\"latitude\":\"not available in demo dataset\",\"longitude\":\"not available in demo dataset\",\"networkLocation\":\"not available in demo dataset\"}","[]","[{'hitNumber': 1, 'time': 0, 'hour': 16, 'minute': 28, 'isSecure': None, 'isInteraction': True, 'isEntrance': True, 'isExit': True, 'referer': 'https://www.google.co.ve/', 'page': {'pagePath': '/google+redesign/electronics/accessories/google+electronics+accessory+pouch.axd', 'hostname': 'shop.googlemerchandisestore.com', 'pageTitle': 'Google Electronics Accessory Pouch', 'searchKeyword': None, 'searchCategory': None, 'pagePathLevel1': '/google+redesign/', 'pagePathLevel2': '/electronics/', 'pagePathLevel3': '/accessories/', 'pagePathLevel4': '/google+electronics+accessory+pouch.axd'}, 'transaction': {'transactionId': None, 'transactionRevenue': None, 'transactionTax': None, 'transactionShipping': None, 'affiliation': None, 'currencyCode': 'USD', 'localTransactionRevenue': None, 'localTransactionTax': None, 'localTransactionShipping': None, 'transactionCoupon': None}, 'item': {'transactionId': None, 'productName': None, 'productCategory': None, 'productSku': None, 'itemQuantity': None, 'itemRevenue': None, 'currencyCode': 'USD', 'localItemRevenue': None}, 'contentInfo': None, 'appInfo': {'name': None, 'version': None, 'id': None, 'installerId': None, 'appInstallerId': None, 'appName': None, 'appVersion': None, 'appId': None, 'screenName': 'shop.googlemerchandisestore.com/google+redesign/electronics/accessories/google+electronics+accessory+pouch.axd', 'landingScreenName': 'shop.googlemerchandisestore.com/google+redesign/electronics/accessories/google+electronics+accessory+pouch.axd', 'exitScreenName': 'shop.googlemerchandisestore.com/google+redesign/electronics/accessories/google+electronics+accessory+pouch.axd', 'screenDepth': '0'}, 'exceptionInfo': {'description': None, 'isFatal': True, 'exceptions': None, 'fatalExceptions': None}, 'eventInfo': None, 'product': array([{'productSKU': '9182714', 'v2ProductName': \"Google Men's Long Sleeve Raglan Ocean Blue\", 'v2ProductCategory': '(not set)', 'productVariant': '(not set)', 'productBrand': '(not set)', 'productRevenue': None, 'localProductRevenue': None, 'productPrice': 0, 'localProductPrice': 0, 'productQuantity': None, 'productRefundAmount': None, 'localProductRefundAmount': None, 'isImpression': True, 'isClick': None, 'customDimensions': array([], dtype=object), 'customMetrics': array([], dtype=object), 'productListName': 'Related Products', 'productListPosition': 1},\n        {'productSKU': '9182502', 'v2ProductName': \"Google Women's Yoga Jacket Black\", 'v2ProductCategory': '(not set)', 'productVariant': '(not set)', 'productBrand': '(not set)', 'productRevenue': None, 'localProductRevenue': None, 'productPrice': 0, 'localProductPrice': 0, 'productQuantity': None, 'productRefundAmount': None, 'localProductRefundAmount': None, 'isImpression': True, 'isClick': None, 'customDimensions': array([], dtype=object), 'customMetrics': array([], dtype=object), 'productListName': 'Related Products', 'productListPosition': 2}],\n       dtype=object), 'promotion': array([], dtype=object), 'promotionActionInfo': None, 'refund': None, 'eCommerceAction': {'action_type': '0', 'step': 1, 'option': None}, 'experiment': array([], dtype=object), 'publisher': None, 'customVariables': array([], dtype=object), 'customDimensions': array([], dtype=object), 'customMetrics': array([], dtype=object), 'type': 'PAGE', 'social': {'socialInteractionNetwork': None, 'socialInteractionAction': None, 'socialInteractions': None, 'socialInteractionTarget': None, 'socialNetwork': '(not set)', 'uniqueSocialInteractions': None, 'hasSocialSourceReferral': 'No', 'socialInteractionNetworkAction': ' : '}, 'latencyTracking': None, 'sourcePropertyInfo': None, 'contentGroup': {'contentGroup1': '(not set)', 'contentGroup2': 'Electronics', 'contentGroup3': '(not set)', 'contentGroup4': '(not set)', 'contentGroup5': '(not set)', 'previousContentGroup1': '(entrance)', 'previousContentGroup2': '(entrance)', 'previousContentGroup3': '(entrance)', 'previousContentGroup4': '(entrance)', 'previousContentGroup5': '(entrance)', 'contentGroupUniqueViews1': None, 'contentGroupUniqueViews2': 1, 'contentGroupUniqueViews3': None, 'contentGroupUniqueViews4': None, 'contentGroupUniqueViews5': None}, 'dataSource': None, 'publisher_infos': array([], dtype=object)}                                                                                                                                                                                                                                                                                                                                                                                                                                                                                                                                                                                                                                                                                                                                                                                                                                                                                                                                                                                                                                                                                             ]","3747703994981981896",null,"Organic Search","Not Socially Engaged"],[null,7,1486413250,1486413250,"20170206","{\"visits\":1,\"hits\":1,\"pageviews\":1,\"timeOnSite\":null,\"bounces\":1,\"transactions\":null,\"transactionRevenue\":null,\"newVisits\":null,\"screenviews\":null,\"uniqueScreenviews\":null,\"timeOnScreen\":null,\"totalTransactionRevenue\":null,\"sessionQualityDim\":null}","{\"referralPath\":null,\"campaign\":\"(not set)\",\"source\":\"(direct)\",\"medium\":\"(none)\",\"keyword\":null,\"adContent\":null,\"adwordsClickInfo\":{\"campaignId\":null,\"adGroupId\":null,\"creativeId\":null,\"criteriaId\":null,\"page\":null,\"slot\":null,\"criteriaParameters\":\"not available in demo dataset\",\"gclId\":null,\"customerId\":null,\"adNetworkType\":null,\"targetingCriteria\":null,\"isVideoAd\":null},\"isTrueDirect\":null,\"campaignCode\":null}","{\"browser\":\"Chrome\",\"browserVersion\":\"not available in demo dataset\",\"browserSize\":\"not available in demo dataset\",\"operatingSystem\":\"Windows\",\"operatingSystemVersion\":\"not available in demo dataset\",\"isMobile\":false,\"mobileDeviceBranding\":\"not available in demo dataset\",\"mobileDeviceModel\":\"not available in demo dataset\",\"mobileInputSelector\":\"not available in demo dataset\",\"mobileDeviceInfo\":\"not available in demo dataset\",\"mobileDeviceMarketingName\":\"not available in demo dataset\",\"flashVersion\":\"not available in demo dataset\",\"javaEnabled\":null,\"language\":\"not available in demo dataset\",\"screenColors\":\"not available in demo dataset\",\"screenResolution\":\"not available in demo dataset\",\"deviceCategory\":\"desktop\"}","{\"continent\":\"Europe\",\"subContinent\":\"Southern Europe\",\"country\":\"Portugal\",\"region\":\"not available in demo dataset\",\"metro\":\"not available in demo dataset\",\"city\":\"not available in demo dataset\",\"cityId\":\"not available in demo dataset\",\"networkDomain\":\"vodafone.pt\",\"latitude\":\"not available in demo dataset\",\"longitude\":\"not available in demo dataset\",\"networkLocation\":\"not available in demo dataset\"}","[]","[{'hitNumber': 1, 'time': 0, 'hour': 12, 'minute': 34, 'isSecure': None, 'isInteraction': True, 'isEntrance': True, 'isExit': True, 'referer': 'https://www.google.pt/', 'page': {'pagePath': '/google+redesign/nest/nest+usa/nest+learning+thermostat+3rd+gen+usa+stainless+steel.axd', 'hostname': 'shop.googlemerchandisestore.com', 'pageTitle': 'Nest® Learning Thermostat 3rd Gen-USA - Stainless Steel', 'searchKeyword': None, 'searchCategory': None, 'pagePathLevel1': '/google+redesign/', 'pagePathLevel2': '/nest/', 'pagePathLevel3': '/nest+usa/', 'pagePathLevel4': '/nest+learning+thermostat+3rd+gen+usa+stainless+steel.axd'}, 'transaction': {'transactionId': None, 'transactionRevenue': None, 'transactionTax': None, 'transactionShipping': None, 'affiliation': None, 'currencyCode': 'USD', 'localTransactionRevenue': None, 'localTransactionTax': None, 'localTransactionShipping': None, 'transactionCoupon': None}, 'item': {'transactionId': None, 'productName': None, 'productCategory': None, 'productSku': None, 'itemQuantity': None, 'itemRevenue': None, 'currencyCode': 'USD', 'localItemRevenue': None}, 'contentInfo': None, 'appInfo': {'name': None, 'version': None, 'id': None, 'installerId': None, 'appInstallerId': None, 'appName': None, 'appVersion': None, 'appId': None, 'screenName': 'shop.googlemerchandisestore.com/google+redesign/nest/nest+usa/nest+learning+thermostat+3rd+gen+usa+stainless+steel.axd', 'landingScreenName': 'shop.googlemerchandisestore.com/google+redesign/nest/nest+usa/nest+learning+thermostat+3rd+gen+usa+stainless+steel.axd', 'exitScreenName': 'shop.googlemerchandisestore.com/google+redesign/nest/nest+usa/nest+learning+thermostat+3rd+gen+usa+stainless+steel.axd', 'screenDepth': '0'}, 'exceptionInfo': {'description': None, 'isFatal': True, 'exceptions': None, 'fatalExceptions': None}, 'eventInfo': None, 'product': array([{'productSKU': '9182737', 'v2ProductName': \"Google Women's 3/4 Sleeve Baseball Raglan Heather/Black\", 'v2ProductCategory': '(not set)', 'productVariant': '(not set)', 'productBrand': '(not set)', 'productRevenue': None, 'localProductRevenue': None, 'productPrice': 0, 'localProductPrice': 0, 'productQuantity': None, 'productRefundAmount': None, 'localProductRefundAmount': None, 'isImpression': True, 'isClick': None, 'customDimensions': array([], dtype=object), 'customMetrics': array([], dtype=object), 'productListName': 'Related Products', 'productListPosition': 1},\n        {'productSKU': '9183232', 'v2ProductName': 'Nest® Protect Smoke + CO Black Battery Alarm-USA', 'v2ProductCategory': '(not set)', 'productVariant': '(not set)', 'productBrand': '(not set)', 'productRevenue': None, 'localProductRevenue': None, 'productPrice': 0, 'localProductPrice': 0, 'productQuantity': None, 'productRefundAmount': None, 'localProductRefundAmount': None, 'isImpression': True, 'isClick': None, 'customDimensions': array([], dtype=object), 'customMetrics': array([], dtype=object), 'productListName': 'Related Products', 'productListPosition': 2}],\n       dtype=object), 'promotion': array([], dtype=object), 'promotionActionInfo': None, 'refund': None, 'eCommerceAction': {'action_type': '0', 'step': 1, 'option': None}, 'experiment': array([], dtype=object), 'publisher': None, 'customVariables': array([], dtype=object), 'customDimensions': array([], dtype=object), 'customMetrics': array([], dtype=object), 'type': 'PAGE', 'social': {'socialInteractionNetwork': None, 'socialInteractionAction': None, 'socialInteractions': None, 'socialInteractionTarget': None, 'socialNetwork': '(not set)', 'uniqueSocialInteractions': None, 'hasSocialSourceReferral': 'No', 'socialInteractionNetworkAction': ' : '}, 'latencyTracking': None, 'sourcePropertyInfo': None, 'contentGroup': {'contentGroup1': '(not set)', 'contentGroup2': 'Nest', 'contentGroup3': '(not set)', 'contentGroup4': '(not set)', 'contentGroup5': '(not set)', 'previousContentGroup1': '(entrance)', 'previousContentGroup2': '(entrance)', 'previousContentGroup3': '(entrance)', 'previousContentGroup4': '(entrance)', 'previousContentGroup5': '(entrance)', 'contentGroupUniqueViews1': None, 'contentGroupUniqueViews2': 1, 'contentGroupUniqueViews3': None, 'contentGroupUniqueViews4': None, 'contentGroupUniqueViews5': None}, 'dataSource': None, 'publisher_infos': array([], dtype=object)}                                                                                                                                                                                                                                                                                                                                                                                                                                                                                                                                                                                                                                                                                                                                                                                                                                                                                                                                                                                                                                                                                                                                                                           ]","092185348184314980",null,"Organic Search","Not Socially Engaged"],[null,1,1486379736,1486379736,"20170206","{\"visits\":1,\"hits\":1,\"pageviews\":1,\"timeOnSite\":null,\"bounces\":1,\"transactions\":null,\"transactionRevenue\":null,\"newVisits\":1,\"screenviews\":null,\"uniqueScreenviews\":null,\"timeOnScreen\":null,\"totalTransactionRevenue\":null,\"sessionQualityDim\":null}","{\"referralPath\":null,\"campaign\":\"(not set)\",\"source\":\"(direct)\",\"medium\":\"(none)\",\"keyword\":null,\"adContent\":null,\"adwordsClickInfo\":{\"campaignId\":null,\"adGroupId\":null,\"creativeId\":null,\"criteriaId\":null,\"page\":null,\"slot\":null,\"criteriaParameters\":\"not available in demo dataset\",\"gclId\":null,\"customerId\":null,\"adNetworkType\":null,\"targetingCriteria\":null,\"isVideoAd\":null},\"isTrueDirect\":null,\"campaignCode\":null}","{\"browser\":\"Safari\",\"browserVersion\":\"not available in demo dataset\",\"browserSize\":\"not available in demo dataset\",\"operatingSystem\":\"Macintosh\",\"operatingSystemVersion\":\"not available in demo dataset\",\"isMobile\":false,\"mobileDeviceBranding\":\"not available in demo dataset\",\"mobileDeviceModel\":\"not available in demo dataset\",\"mobileInputSelector\":\"not available in demo dataset\",\"mobileDeviceInfo\":\"not available in demo dataset\",\"mobileDeviceMarketingName\":\"not available in demo dataset\",\"flashVersion\":\"not available in demo dataset\",\"javaEnabled\":null,\"language\":\"not available in demo dataset\",\"screenColors\":\"not available in demo dataset\",\"screenResolution\":\"not available in demo dataset\",\"deviceCategory\":\"desktop\"}","{\"continent\":\"Europe\",\"subContinent\":\"Southern Europe\",\"country\":\"Italy\",\"region\":\"not available in demo dataset\",\"metro\":\"not available in demo dataset\",\"city\":\"not available in demo dataset\",\"cityId\":\"not available in demo dataset\",\"networkDomain\":\"telecomitalia.it\",\"latitude\":\"not available in demo dataset\",\"longitude\":\"not available in demo dataset\",\"networkLocation\":\"not available in demo dataset\"}","[{'index': 4, 'value': 'EMEA'}]","[{'hitNumber': 1, 'time': 0, 'hour': 3, 'minute': 15, 'isSecure': None, 'isInteraction': True, 'isEntrance': True, 'isExit': True, 'referer': 'https://www.google.it/', 'page': {'pagePath': '/google+redesign/bags', 'hostname': 'shop.googlemerchandisestore.com', 'pageTitle': 'Bags | Google Merchandise Store', 'searchKeyword': None, 'searchCategory': None, 'pagePathLevel1': '/google+redesign/', 'pagePathLevel2': '/bags', 'pagePathLevel3': '', 'pagePathLevel4': ''}, 'transaction': {'transactionId': None, 'transactionRevenue': None, 'transactionTax': None, 'transactionShipping': None, 'affiliation': None, 'currencyCode': 'USD', 'localTransactionRevenue': None, 'localTransactionTax': None, 'localTransactionShipping': None, 'transactionCoupon': None}, 'item': {'transactionId': None, 'productName': None, 'productCategory': None, 'productSku': None, 'itemQuantity': None, 'itemRevenue': None, 'currencyCode': 'USD', 'localItemRevenue': None}, 'contentInfo': None, 'appInfo': {'name': None, 'version': None, 'id': None, 'installerId': None, 'appInstallerId': None, 'appName': None, 'appVersion': None, 'appId': None, 'screenName': 'shop.googlemerchandisestore.com/google+redesign/bags', 'landingScreenName': 'shop.googlemerchandisestore.com/google+redesign/bags', 'exitScreenName': 'shop.googlemerchandisestore.com/google+redesign/bags', 'screenDepth': '0'}, 'exceptionInfo': {'description': None, 'isFatal': True, 'exceptions': None, 'fatalExceptions': None}, 'eventInfo': None, 'product': array([{'productSKU': 'GGOEGCLB020832', 'v2ProductName': 'Softsided Travel Pouch Set', 'v2ProductCategory': 'Home/Bags/', 'productVariant': '(not set)', 'productBrand': '(not set)', 'productRevenue': None, 'localProductRevenue': None, 'productPrice': 10990000, 'localProductPrice': 10990000, 'productQuantity': None, 'productRefundAmount': None, 'localProductRefundAmount': None, 'isImpression': True, 'isClick': None, 'customDimensions': array([], dtype=object), 'customMetrics': array([], dtype=object), 'productListName': 'Category', 'productListPosition': 1},\n        {'productSKU': 'GGOEGCMB020932', 'v2ProductName': 'Suitcase Organizer Cubes', 'v2ProductCategory': 'Home/Bags/', 'productVariant': '(not set)', 'productBrand': '(not set)', 'productRevenue': None, 'localProductRevenue': None, 'productPrice': 21990000, 'localProductPrice': 21990000, 'productQuantity': None, 'productRefundAmount': None, 'localProductRefundAmount': None, 'isImpression': True, 'isClick': None, 'customDimensions': array([], dtype=object), 'customMetrics': array([], dtype=object), 'productListName': 'Category', 'productListPosition': 2},\n        {'productSKU': 'GGOEGBFC018799', 'v2ProductName': 'Electronics Accessory Pouch', 'v2ProductCategory': 'Home/Bags/', 'productVariant': '(not set)', 'productBrand': '(not set)', 'productRevenue': None, 'localProductRevenue': None, 'productPrice': 4990000, 'localProductPrice': 4990000, 'productQuantity': None, 'productRefundAmount': None, 'localProductRefundAmount': None, 'isImpression': True, 'isClick': None, 'customDimensions': array([], dtype=object), 'customMetrics': array([], dtype=object), 'productListName': 'Category', 'productListPosition': 3},\n        {'productSKU': 'GGOEGBMJ013399', 'v2ProductName': 'Sport Bag', 'v2ProductCategory': 'Home/Bags/', 'productVariant': '(not set)', 'productBrand': '(not set)', 'productRevenue': None, 'localProductRevenue': None, 'productPrice': 4990000, 'localProductPrice': 4990000, 'productQuantity': None, 'productRefundAmount': None, 'localProductRefundAmount': None, 'isImpression': True, 'isClick': None, 'customDimensions': array([], dtype=object), 'customMetrics': array([], dtype=object), 'productListName': 'Category', 'productListPosition': 4},\n        {'productSKU': 'GGOEGBCR024399', 'v2ProductName': 'Google Lunch Bag', 'v2ProductCategory': 'Home/Bags/', 'productVariant': '(not set)', 'productBrand': '(not set)', 'productRevenue': None, 'localProductRevenue': None, 'productPrice': 13990000, 'localProductPrice': 13990000, 'productQuantity': None, 'productRefundAmount': None, 'localProductRefundAmount': None, 'isImpression': True, 'isClick': None, 'customDimensions': array([], dtype=object), 'customMetrics': array([], dtype=object), 'productListName': 'Category', 'productListPosition': 5},\n        {'productSKU': 'GGOEGBJC014399', 'v2ProductName': 'Google Tote Bag', 'v2ProductCategory': 'Home/Bags/', 'productVariant': '(not set)', 'productBrand': '(not set)', 'productRevenue': None, 'localProductRevenue': None, 'productPrice': 9990000, 'localProductPrice': 9990000, 'productQuantity': None, 'productRefundAmount': None, 'localProductRefundAmount': None, 'isImpression': True, 'isClick': None, 'customDimensions': array([], dtype=object), 'customMetrics': array([], dtype=object), 'productListName': 'Category', 'productListPosition': 6},\n        {'productSKU': 'GGOEGBJC019999', 'v2ProductName': 'Collapsible Shopping Bag', 'v2ProductCategory': 'Home/Bags/', 'productVariant': '(not set)', 'productBrand': '(not set)', 'productRevenue': None, 'localProductRevenue': None, 'productPrice': 4990000, 'localProductPrice': 4990000, 'productQuantity': None, 'productRefundAmount': None, 'localProductRefundAmount': None, 'isImpression': True, 'isClick': None, 'customDimensions': array([], dtype=object), 'customMetrics': array([], dtype=object), 'productListName': 'Category', 'productListPosition': 7},\n        {'productSKU': 'GGOEGBRJ037299', 'v2ProductName': 'Google Alpine Style Backpack', 'v2ProductCategory': 'Home/Bags/', 'productVariant': '(not set)', 'productBrand': '(not set)', 'productRevenue': None, 'localProductRevenue': None, 'productPrice': 99990000, 'localProductPrice': 99990000, 'productQuantity': None, 'productRefundAmount': None, 'localProductRefundAmount': None, 'isImpression': True, 'isClick': None, 'customDimensions': array([], dtype=object), 'customMetrics': array([], dtype=object), 'productListName': 'Category', 'productListPosition': 8},\n        {'productSKU': 'GGOEGBMB073799', 'v2ProductName': 'Google Zipper-front Sports Bag', 'v2ProductCategory': 'Home/Bags/', 'productVariant': '(not set)', 'productBrand': '(not set)', 'productRevenue': None, 'localProductRevenue': None, 'productPrice': 19990000, 'localProductPrice': 19990000, 'productQuantity': None, 'productRefundAmount': None, 'localProductRefundAmount': None, 'isImpression': True, 'isClick': None, 'customDimensions': array([], dtype=object), 'customMetrics': array([], dtype=object), 'productListName': 'Category', 'productListPosition': 9},\n        {'productSKU': 'GGOEGBRA037499', 'v2ProductName': 'Waterproof Backpack', 'v2ProductCategory': 'Home/Bags/', 'productVariant': '(not set)', 'productBrand': '(not set)', 'productRevenue': None, 'localProductRevenue': None, 'productPrice': 99990000, 'localProductPrice': 99990000, 'productQuantity': None, 'productRefundAmount': None, 'localProductRefundAmount': None, 'isImpression': True, 'isClick': None, 'customDimensions': array([], dtype=object), 'customMetrics': array([], dtype=object), 'productListName': 'Category', 'productListPosition': 10},\n        {'productSKU': 'GGOEGBJL013999', 'v2ProductName': 'Google Canvas Tote Natural/Navy', 'v2ProductCategory': 'Home/Bags/', 'productVariant': '(not set)', 'productBrand': '(not set)', 'productRevenue': None, 'localProductRevenue': None, 'productPrice': 15990000, 'localProductPrice': 15990000, 'productQuantity': None, 'productRefundAmount': None, 'localProductRefundAmount': None, 'isImpression': True, 'isClick': None, 'customDimensions': array([], dtype=object), 'customMetrics': array([], dtype=object), 'productListName': 'Category', 'productListPosition': 11},\n        {'productSKU': 'GGOEGBPB021199', 'v2ProductName': 'Google Slim Utility Travel Bag', 'v2ProductCategory': 'Home/Bags/', 'productVariant': '(not set)', 'productBrand': '(not set)', 'productRevenue': None, 'localProductRevenue': None, 'productPrice': 14990000, 'localProductPrice': 14990000, 'productQuantity': None, 'productRefundAmount': None, 'localProductRefundAmount': None, 'isImpression': True, 'isClick': None, 'customDimensions': array([], dtype=object), 'customMetrics': array([], dtype=object), 'productListName': 'Category', 'productListPosition': 12}],\n       dtype=object), 'promotion': array([], dtype=object), 'promotionActionInfo': None, 'refund': None, 'eCommerceAction': {'action_type': '0', 'step': 1, 'option': None}, 'experiment': array([], dtype=object), 'publisher': None, 'customVariables': array([], dtype=object), 'customDimensions': array([], dtype=object), 'customMetrics': array([], dtype=object), 'type': 'PAGE', 'social': {'socialInteractionNetwork': None, 'socialInteractionAction': None, 'socialInteractions': None, 'socialInteractionTarget': None, 'socialNetwork': '(not set)', 'uniqueSocialInteractions': None, 'hasSocialSourceReferral': 'No', 'socialInteractionNetworkAction': ' : '}, 'latencyTracking': None, 'sourcePropertyInfo': None, 'contentGroup': {'contentGroup1': '(not set)', 'contentGroup2': 'Bags', 'contentGroup3': '(not set)', 'contentGroup4': '(not set)', 'contentGroup5': '(not set)', 'previousContentGroup1': '(entrance)', 'previousContentGroup2': '(entrance)', 'previousContentGroup3': '(entrance)', 'previousContentGroup4': '(entrance)', 'previousContentGroup5': '(entrance)', 'contentGroupUniqueViews1': None, 'contentGroupUniqueViews2': 1, 'contentGroupUniqueViews3': None, 'contentGroupUniqueViews4': None, 'contentGroupUniqueViews5': None}, 'dataSource': None, 'publisher_infos': array([], dtype=object)}                                                                                                                                                                                                                                                                                                                                                                                                                                                                                                                                                                                                                                                                                                                                                                                       ]","1041385895383811958",null,"Organic Search","Not Socially Engaged"],[null,1,1486414367,1486414367,"20170206","{\"visits\":1,\"hits\":1,\"pageviews\":1,\"timeOnSite\":null,\"bounces\":1,\"transactions\":null,\"transactionRevenue\":null,\"newVisits\":1,\"screenviews\":null,\"uniqueScreenviews\":null,\"timeOnScreen\":null,\"totalTransactionRevenue\":null,\"sessionQualityDim\":null}","{\"referralPath\":null,\"campaign\":\"(not set)\",\"source\":\"(direct)\",\"medium\":\"(none)\",\"keyword\":null,\"adContent\":null,\"adwordsClickInfo\":{\"campaignId\":null,\"adGroupId\":null,\"creativeId\":null,\"criteriaId\":null,\"page\":null,\"slot\":null,\"criteriaParameters\":\"not available in demo dataset\",\"gclId\":null,\"customerId\":null,\"adNetworkType\":null,\"targetingCriteria\":null,\"isVideoAd\":null},\"isTrueDirect\":null,\"campaignCode\":null}","{\"browser\":\"Chrome\",\"browserVersion\":\"not available in demo dataset\",\"browserSize\":\"not available in demo dataset\",\"operatingSystem\":\"Android\",\"operatingSystemVersion\":\"not available in demo dataset\",\"isMobile\":true,\"mobileDeviceBranding\":\"not available in demo dataset\",\"mobileDeviceModel\":\"not available in demo dataset\",\"mobileInputSelector\":\"not available in demo dataset\",\"mobileDeviceInfo\":\"not available in demo dataset\",\"mobileDeviceMarketingName\":\"not available in demo dataset\",\"flashVersion\":\"not available in demo dataset\",\"javaEnabled\":null,\"language\":\"not available in demo dataset\",\"screenColors\":\"not available in demo dataset\",\"screenResolution\":\"not available in demo dataset\",\"deviceCategory\":\"mobile\"}","{\"continent\":\"Asia\",\"subContinent\":\"Eastern Asia\",\"country\":\"Hong Kong\",\"region\":\"(not set)\",\"metro\":\"(not set)\",\"city\":\"Hong Kong\",\"cityId\":\"not available in demo dataset\",\"networkDomain\":\"netvigator.com\",\"latitude\":\"not available in demo dataset\",\"longitude\":\"not available in demo dataset\",\"networkLocation\":\"not available in demo dataset\"}","[]","[{'hitNumber': 1, 'time': 0, 'hour': 12, 'minute': 52, 'isSecure': None, 'isInteraction': True, 'isEntrance': True, 'isExit': True, 'referer': 'https://www.google.com.hk/', 'page': {'pagePath': '/google+redesign/bags', 'hostname': 'shop.googlemerchandisestore.com', 'pageTitle': 'Bags | Google Merchandise Store', 'searchKeyword': None, 'searchCategory': None, 'pagePathLevel1': '/google+redesign/', 'pagePathLevel2': '/bags', 'pagePathLevel3': '', 'pagePathLevel4': ''}, 'transaction': {'transactionId': None, 'transactionRevenue': None, 'transactionTax': None, 'transactionShipping': None, 'affiliation': None, 'currencyCode': 'USD', 'localTransactionRevenue': None, 'localTransactionTax': None, 'localTransactionShipping': None, 'transactionCoupon': None}, 'item': {'transactionId': None, 'productName': None, 'productCategory': None, 'productSku': None, 'itemQuantity': None, 'itemRevenue': None, 'currencyCode': 'USD', 'localItemRevenue': None}, 'contentInfo': None, 'appInfo': {'name': None, 'version': None, 'id': None, 'installerId': None, 'appInstallerId': None, 'appName': None, 'appVersion': None, 'appId': None, 'screenName': 'shop.googlemerchandisestore.com/google+redesign/bags', 'landingScreenName': 'shop.googlemerchandisestore.com/google+redesign/bags', 'exitScreenName': 'shop.googlemerchandisestore.com/google+redesign/bags', 'screenDepth': '0'}, 'exceptionInfo': {'description': None, 'isFatal': True, 'exceptions': None, 'fatalExceptions': None}, 'eventInfo': None, 'product': array([{'productSKU': 'GGOEGCLB020832', 'v2ProductName': 'Softsided Travel Pouch Set', 'v2ProductCategory': 'Home/Bags/', 'productVariant': '(not set)', 'productBrand': '(not set)', 'productRevenue': None, 'localProductRevenue': None, 'productPrice': 10990000, 'localProductPrice': 10990000, 'productQuantity': None, 'productRefundAmount': None, 'localProductRefundAmount': None, 'isImpression': True, 'isClick': None, 'customDimensions': array([], dtype=object), 'customMetrics': array([], dtype=object), 'productListName': 'Category', 'productListPosition': 1},\n        {'productSKU': 'GGOEGCMB020932', 'v2ProductName': 'Suitcase Organizer Cubes', 'v2ProductCategory': 'Home/Bags/', 'productVariant': '(not set)', 'productBrand': '(not set)', 'productRevenue': None, 'localProductRevenue': None, 'productPrice': 21990000, 'localProductPrice': 21990000, 'productQuantity': None, 'productRefundAmount': None, 'localProductRefundAmount': None, 'isImpression': True, 'isClick': None, 'customDimensions': array([], dtype=object), 'customMetrics': array([], dtype=object), 'productListName': 'Category', 'productListPosition': 2},\n        {'productSKU': 'GGOEGBFC018799', 'v2ProductName': 'Electronics Accessory Pouch', 'v2ProductCategory': 'Home/Bags/', 'productVariant': '(not set)', 'productBrand': '(not set)', 'productRevenue': None, 'localProductRevenue': None, 'productPrice': 4990000, 'localProductPrice': 4990000, 'productQuantity': None, 'productRefundAmount': None, 'localProductRefundAmount': None, 'isImpression': True, 'isClick': None, 'customDimensions': array([], dtype=object), 'customMetrics': array([], dtype=object), 'productListName': 'Category', 'productListPosition': 3},\n        {'productSKU': 'GGOEGBMJ013399', 'v2ProductName': 'Sport Bag', 'v2ProductCategory': 'Home/Bags/', 'productVariant': '(not set)', 'productBrand': '(not set)', 'productRevenue': None, 'localProductRevenue': None, 'productPrice': 4990000, 'localProductPrice': 4990000, 'productQuantity': None, 'productRefundAmount': None, 'localProductRefundAmount': None, 'isImpression': True, 'isClick': None, 'customDimensions': array([], dtype=object), 'customMetrics': array([], dtype=object), 'productListName': 'Category', 'productListPosition': 4},\n        {'productSKU': 'GGOEGBCR024399', 'v2ProductName': 'Google Lunch Bag', 'v2ProductCategory': 'Home/Bags/', 'productVariant': '(not set)', 'productBrand': '(not set)', 'productRevenue': None, 'localProductRevenue': None, 'productPrice': 13990000, 'localProductPrice': 13990000, 'productQuantity': None, 'productRefundAmount': None, 'localProductRefundAmount': None, 'isImpression': True, 'isClick': None, 'customDimensions': array([], dtype=object), 'customMetrics': array([], dtype=object), 'productListName': 'Category', 'productListPosition': 5},\n        {'productSKU': 'GGOEGBJC014399', 'v2ProductName': 'Google Tote Bag', 'v2ProductCategory': 'Home/Bags/', 'productVariant': '(not set)', 'productBrand': '(not set)', 'productRevenue': None, 'localProductRevenue': None, 'productPrice': 9990000, 'localProductPrice': 9990000, 'productQuantity': None, 'productRefundAmount': None, 'localProductRefundAmount': None, 'isImpression': True, 'isClick': None, 'customDimensions': array([], dtype=object), 'customMetrics': array([], dtype=object), 'productListName': 'Category', 'productListPosition': 6},\n        {'productSKU': 'GGOEGBJC019999', 'v2ProductName': 'Collapsible Shopping Bag', 'v2ProductCategory': 'Home/Bags/', 'productVariant': '(not set)', 'productBrand': '(not set)', 'productRevenue': None, 'localProductRevenue': None, 'productPrice': 4990000, 'localProductPrice': 4990000, 'productQuantity': None, 'productRefundAmount': None, 'localProductRefundAmount': None, 'isImpression': True, 'isClick': None, 'customDimensions': array([], dtype=object), 'customMetrics': array([], dtype=object), 'productListName': 'Category', 'productListPosition': 7},\n        {'productSKU': 'GGOEGBRJ037299', 'v2ProductName': 'Google Alpine Style Backpack', 'v2ProductCategory': 'Home/Bags/', 'productVariant': '(not set)', 'productBrand': '(not set)', 'productRevenue': None, 'localProductRevenue': None, 'productPrice': 99990000, 'localProductPrice': 99990000, 'productQuantity': None, 'productRefundAmount': None, 'localProductRefundAmount': None, 'isImpression': True, 'isClick': None, 'customDimensions': array([], dtype=object), 'customMetrics': array([], dtype=object), 'productListName': 'Category', 'productListPosition': 8},\n        {'productSKU': 'GGOEGBMB073799', 'v2ProductName': 'Google Zipper-front Sports Bag', 'v2ProductCategory': 'Home/Bags/', 'productVariant': '(not set)', 'productBrand': '(not set)', 'productRevenue': None, 'localProductRevenue': None, 'productPrice': 19990000, 'localProductPrice': 19990000, 'productQuantity': None, 'productRefundAmount': None, 'localProductRefundAmount': None, 'isImpression': True, 'isClick': None, 'customDimensions': array([], dtype=object), 'customMetrics': array([], dtype=object), 'productListName': 'Category', 'productListPosition': 9},\n        {'productSKU': 'GGOEGBRA037499', 'v2ProductName': 'Waterproof Backpack', 'v2ProductCategory': 'Home/Bags/', 'productVariant': '(not set)', 'productBrand': '(not set)', 'productRevenue': None, 'localProductRevenue': None, 'productPrice': 99990000, 'localProductPrice': 99990000, 'productQuantity': None, 'productRefundAmount': None, 'localProductRefundAmount': None, 'isImpression': True, 'isClick': None, 'customDimensions': array([], dtype=object), 'customMetrics': array([], dtype=object), 'productListName': 'Category', 'productListPosition': 10},\n        {'productSKU': 'GGOEGBJL013999', 'v2ProductName': 'Google Canvas Tote Natural/Navy', 'v2ProductCategory': 'Home/Bags/', 'productVariant': '(not set)', 'productBrand': '(not set)', 'productRevenue': None, 'localProductRevenue': None, 'productPrice': 15990000, 'localProductPrice': 15990000, 'productQuantity': None, 'productRefundAmount': None, 'localProductRefundAmount': None, 'isImpression': True, 'isClick': None, 'customDimensions': array([], dtype=object), 'customMetrics': array([], dtype=object), 'productListName': 'Category', 'productListPosition': 11},\n        {'productSKU': 'GGOEGBPB021199', 'v2ProductName': 'Google Slim Utility Travel Bag', 'v2ProductCategory': 'Home/Bags/', 'productVariant': '(not set)', 'productBrand': '(not set)', 'productRevenue': None, 'localProductRevenue': None, 'productPrice': 14990000, 'localProductPrice': 14990000, 'productQuantity': None, 'productRefundAmount': None, 'localProductRefundAmount': None, 'isImpression': True, 'isClick': None, 'customDimensions': array([], dtype=object), 'customMetrics': array([], dtype=object), 'productListName': 'Category', 'productListPosition': 12}],\n       dtype=object), 'promotion': array([], dtype=object), 'promotionActionInfo': None, 'refund': None, 'eCommerceAction': {'action_type': '0', 'step': 1, 'option': None}, 'experiment': array([], dtype=object), 'publisher': None, 'customVariables': array([], dtype=object), 'customDimensions': array([], dtype=object), 'customMetrics': array([], dtype=object), 'type': 'PAGE', 'social': {'socialInteractionNetwork': None, 'socialInteractionAction': None, 'socialInteractions': None, 'socialInteractionTarget': None, 'socialNetwork': '(not set)', 'uniqueSocialInteractions': None, 'hasSocialSourceReferral': 'No', 'socialInteractionNetworkAction': ' : '}, 'latencyTracking': None, 'sourcePropertyInfo': None, 'contentGroup': {'contentGroup1': '(not set)', 'contentGroup2': 'Bags', 'contentGroup3': '(not set)', 'contentGroup4': '(not set)', 'contentGroup5': '(not set)', 'previousContentGroup1': '(entrance)', 'previousContentGroup2': '(entrance)', 'previousContentGroup3': '(entrance)', 'previousContentGroup4': '(entrance)', 'previousContentGroup5': '(entrance)', 'contentGroupUniqueViews1': None, 'contentGroupUniqueViews2': 1, 'contentGroupUniqueViews3': None, 'contentGroupUniqueViews4': None, 'contentGroupUniqueViews5': None}, 'dataSource': None, 'publisher_infos': array([], dtype=object)}                                                                                                                                                                                                                                                                                                                                                                                                                                                                                                                                                                                                                                                                                                                                                                                            ]","44992025479320911",null,"Organic Search","Not Socially Engaged"]]